AUTHORS.rst
CONTRIBUTING.rst
HISTORY.rst
LICENSE
MANIFEST.in
README.rst
setup.cfg
setup.py
browserstep/__init__.py
browserstep/common.py
browserstep/debug.py
browserstep/popup.py
browserstep/sentmail.py
browserstep/timetravel.py
browserstep.egg-info/PKG-INFO
browserstep.egg-info/SOURCES.txt
browserstep.egg-info/dependency_links.txt
browserstep.egg-info/not-zip-safe
browserstep.egg-info/top_level.txt
docs/Makefile
docs/authors.rst
docs/conf.py
docs/contributing.rst
docs/history.rst
docs/index.rst
docs/installation.rst
docs/make.bat
docs/readme.rst
docs/usage.rst
tests/__init__.py
tests/test_browserstep.py