Metadata-Version: 1.1
Name: browserstep
Version: 0.1.9
Summary: Browser step provides common steps to be used by Behave for running browser tests with Selenium
Home-page: https://github.com/thejimmyg/browserstep
Author: James Gardner
Author-email: james@pythonweb.org
License: MIT license
Keywords: browserstep
Platform: UNKNOWN
Classifier: Development Status :: 2 - Pre-Alpha
Classifier: Intended Audience :: Developers
Classifier: License :: OSI Approved :: MIT License
Classifier: Natural Language :: English
Classifier: Programming Language :: Python :: 2
Classifier: Programming Language :: Python :: 2.6
Classifier: Programming Language :: Python :: 2.7
Classifier: Programming Language :: Python :: 3
Classifier: Programming Language :: Python :: 3.3
Classifier: Programming Language :: Python :: 3.4
Classifier: Programming Language :: Python :: 3.5
